waldur_core/__init__.py
waldur_core/core/__init__.py
waldur_core/core/admin.py
waldur_core/core/apps.py
waldur_core/core/authentication.py
waldur_core/core/csv.py
waldur_core/core/docs.py
waldur_core/core/exceptions.py
waldur_core/core/executors.py
waldur_core/core/fields.py
waldur_core/core/filters.py
waldur_core/core/handlers.py
waldur_core/core/log.py
waldur_core/core/magic.py
waldur_core/core/managers.py
waldur_core/core/mixins.py
waldur_core/core/models.py
waldur_core/core/monkeypatch.py
waldur_core/core/pagination.py
waldur_core/core/permissions.py
waldur_core/core/renderers.py
waldur_core/core/routers.py
waldur_core/core/schemas.py
waldur_core/core/serializers.py
waldur_core/core/signals.py
waldur_core/core/tasks.py
waldur_core/core/test_runner.py
waldur_core/core/utils.py
waldur_core/core/validators.py
waldur_core/core/views.py
waldur_core/core/management/__init__.py
waldur_core/core/management/commands/__init__.py
waldur_core/core/management/commands/createstaffuser.py
waldur_core/core/management/commands/drfdocs.py
waldur_core/core/management/commands/export_api_docs.py
waldur_core/core/management/commands/pgmigrate.py
waldur_core/core/management/commands/removestalect.py
waldur_core/core/migrations/0001_squashed_0003_ssh_key_name_length_changed.py
waldur_core/core/migrations/0001_squashed_0008.py
waldur_core/core/migrations/0002_enlarge_civil_number_user_field.py
waldur_core/core/migrations/0002_remove_organization.py
waldur_core/core/migrations/0003_user_registration_method.py
waldur_core/core/migrations/0004_user_agreement_date.py
waldur_core/core/migrations/0005_add_user_language_and_competence.py
waldur_core/core/migrations/0006_user_is_support.py
waldur_core/core/migrations/0007_user_token_lifetime.py
waldur_core/core/migrations/0008_sshpublickey_is_shared.py
waldur_core/core/migrations/__init__.py
waldur_core/core/templates/admin/core/change_list.html
waldur_core-0.161.4.dist-info/METADATA
waldur_core-0.161.4.dist-info/RECORD
waldur_core-0.161.4.dist-info/WHEEL
waldur_core-0.161.4.dist-info/entry_points.txt
waldur_core-0.161.4.dist-info/top_level.txt
