Metadata-Version: 2.1
Name: waldur-core
Version: 0.161.4
Summary: Waldur core is a core of Waldur cloud management service.
Home-page: https://github.com/opennode/waldur-core
Author: OpenNode Team
Author-email: info@opennodecloud.com
License: UNKNOWN
Platform: UNKNOWN
Classifier: Framework :: Django
Classifier: Intended Audience :: Developers
Classifier: Intended Audience :: System Administrators
Classifier: License :: OSI Approved :: MIT License
Classifier: Operating System :: OS Independent
Provides-Extra: tests
Provides-Extra: dev
Requires-Dist: Celery (==4.1.0)
Requires-Dist: croniter (<0.3.6,>=0.3.4)
Requires-Dist: cryptography
Requires-Dist: Django (<2.0,>=1.11)
Requires-Dist: django-admin-tools (==0.8.0)
Requires-Dist: django-defender (>=0.5.3)
Requires-Dist: django-filter (==1.0.2)
Requires-Dist: django-fluent-dashboard (==0.6.1)
Requires-Dist: django-fsm (==2.3.0)
Requires-Dist: django-jsoneditor (>=0.0.7)
Requires-Dist: django-model-utils (==3.0.0)
Requires-Dist: django-redis-cache (>=1.6.5)
Requires-Dist: django-reversion (==2.0.8)
Requires-Dist: django-rest-swagger (==2.1.2)
Requires-Dist: django-taggit (>=0.20.2)
Requires-Dist: djangorestframework (<3.7.0,>=3.6.3)
Requires-Dist: elasticsearch (==5.4.0)
Requires-Dist: hiredis (>=0.2.0)
Requires-Dist: iptools (>=0.6.1)
Requires-Dist: PrettyTable (<0.8,>=0.7.1)
Requires-Dist: Pillow (>=2.0.0)
Requires-Dist: psycopg2 (>=2.5.4)
Requires-Dist: PyYAML (>=3.10)
Requires-Dist: pycountry (<2.0,>=1.20)
Requires-Dist: pyvat (<2.0,>=1.3.1)
Requires-Dist: redis (==2.10.6)
Requires-Dist: requests (!=2.12.2,!=2.13.0,>=2.6.0)
Requires-Dist: sqlparse (>=0.1.11)
Provides-Extra: dev
Requires-Dist: Sphinx (==1.2.2); extra == 'dev'
Provides-Extra: tests
Requires-Dist: ddt (<1.1.0,>=1.0.0); extra == 'tests'
Requires-Dist: factory-boy (==2.4.1); extra == 'tests'
Requires-Dist: freezegun (==0.3.7); extra == 'tests'
Requires-Dist: mock (>=1.0.1); extra == 'tests'
Requires-Dist: mock-django (==0.6.9); extra == 'tests'
Requires-Dist: six (>=1.9.0); extra == 'tests'
Requires-Dist: sqlalchemy (>=1.0.12); extra == 'tests'
